mdformat_dollarmath/__init__.py
mdformat_dollarmath/plugin.py
mdformat_dollarmath-0.0.5.dist-info/entry_points.txt
mdformat_dollarmath-0.0.5.dist-info/licenses/LICENSE
mdformat_dollarmath-0.0.5.dist-info/WHEEL
mdformat_dollarmath-0.0.5.dist-info/METADATA
mdformat_dollarmath-0.0.5.dist-info/RECORD
