Metadata-Version: 2.4
Name: mdformat_dollarmath
Version: 0.0.5
Summary: An mdformat plugin for formatting dollarmath.
Keywords: mdformat,markdown,markdown-it
Author-email: Livin Nector <livinnector2001@gmail.com>
Requires-Python: >=3.8
Classifier: Intended Audience :: Developers
Classifier: License :: OSI Approved :: MIT License
Classifier: Programming Language :: Python :: 3
Classifier: Topic :: Software Development :: Libraries :: Python Modules
License-File: LICENSE
Requires-Dist: mdformat >=0.7.0,<0.8.0
Requires-Dist: mdit-py-plugins>=0.3.5
Requires-Dist: pre-commit ; extra == "dev"
Requires-Dist: pytest ; extra == "test"
Requires-Dist: coverage ; extra == "test"
Requires-Dist: pytest-cov ; extra == "test"
Project-URL: Homepage, https://github.com/livinNector/mdformat-dollarmath
Provides-Extra: dev
Provides-Extra: test
